DomainClassifier/__init__.py
DomainClassifier/domainclassifier.py
DomainClassifier/test.py
DomainClassifier-1.0.dist-info/DESCRIPTION.rst
DomainClassifier-1.0.dist-info/METADATA
DomainClassifier-1.0.dist-info/RECORD
DomainClassifier-1.0.dist-info/WHEEL
DomainClassifier-1.0.dist-info/dependency_links.txt
DomainClassifier-1.0.dist-info/metadata.json
DomainClassifier-1.0.dist-info/top_level.txt
