Metadata-Version: 2.0
Name: DomainClassifier
Version: 1.0
Summary: DomainClassifier is a Python library to extract and classify Internet domains/hostnames/IP addresses from raw unstructured text files following their existence, localization or attributes.
Home-page: http://github.com/adulau/DomainClassifier
Author: Alexandre Dulaunoy
Author-email: a@foo.be
License: AGPL
Keywords: internet mining domain resolver geolocalisation
Platform: UNKNOWN
Requires-Dist: dnspython
Requires-Dist: IPy
Requires-Dist: pybgpranking
